jaredtest1.py
jaredtest1-0.0.1.dist-info/METADATA
jaredtest1-0.0.1.dist-info/WHEEL
jaredtest1-0.0.1.dist-info/top_level.txt
jaredtest1-0.0.1.dist-info/RECORD
